hithere.py
hithere-0.0.1.dist-info/LICENSE.txt
hithere-0.0.1.dist-info/METADATA
hithere-0.0.1.dist-info/WHEEL
hithere-0.0.1.dist-info/top_level.txt
hithere-0.0.1.dist-info/RECORD
